{
  "nodes" : [
    {
      "node" : {
        "nid" : "18",
        "title" : "<a href=\"/accommodations/whistlewood-farm\">WhistleWood Farm</a>",
        "description" : "Bro ipsum dolor sit amet over the bars brain bucket newschooler, afterbang drop steeps huck hurl...",
        "image_path" : null,
        "link" : "<a href=\"/accommodations/whistlewood-farm\">More Detail &raquo;</a>",
        "path" : "/accommodations/whistlewood-farm",
        "type" : "accommodation",
        "latitude" : "41.946101000000",
        "longitude" : "-73.862626000000",
        "location" : "52 Pells Road Rhinebeck NY 12572 US",
        "category" : "Bed and Breakfasts",
        "tid" : "1",
        "marker" : "marker_1"
      }
    },
    {
      "node" : {
        "nid" : "16",
        "title" : "<a href=\"/accommodations/westin-riverfront-resort\">Westin Riverfront Resort</a>",
        "description" : "Bro ipsum dolor sit amet avie stoked schraeder frontside grab washboard bump snake bite taco bonk....",
        "image_path" : "http://destination.localhost/sites/default/files/styles/thumbnail/public/multiple_images/image01.jpg?itok=mf1NNLMO",
        "link" : "<a href=\"/accommodations/westin-riverfront-resort\">More Detail &raquo;</a>",
        "path" : "/accommodations/westin-riverfront-resort",
        "type" : "accommodation",
        "latitude" : "39.632907000000",
        "longitude" : "-106.524591000000",
        "location" : "126 Riverfront Lane Avon CO 81620 US",
        "category" : "Hotels and Motels",
        "tid" : "4",
        "marker" : "marker_4"
      }
    },
    {
      "node" : {
        "nid" : "26",
        "title" : "<a href=\"/things-to-do/keg-steakhouse-and-bar\">The Keg Steakhouse and Bar</a>",
        "description" : "Bro ipsum dolor sit amet backside Whistler pipe schwag face shots ollie flow gorby grind ollie Ski...",
        "image_path" : "http://destination.localhost/sites/default/files/styles/thumbnail/public/multiple_images/image01_0.jpg?itok=u1oHuPHE",
        "link" : "<a href=\"/things-to-do/keg-steakhouse-and-bar\">More Detail &raquo;</a>",
        "path" : "/things-to-do/keg-steakhouse-and-bar",
        "type" : "things_to_do",
        "latitude" : "53.913768300000",
        "longitude" : "-122.744576400000",
        "location" : "582 George Street Prince George BC V2L 1R7 CA",
        "category" : "Dining and Nightlife;Groups",
        "tid" : "6;9",
        "marker" : "marker_6;marker_9"
      }
    },
    {
      "node" : {
        "nid" : "17",
        "title" : "<a href=\"/accommodations/fairmont-chateau-lake-louise\">Fairmont Chateau Lake Louise</a>",
        "description" : "Bro ipsum dolor sit amet hellflip first tracks tele dust on crust taco glove sharkbite bail hot...",
        "image_path" : "http://destination.localhost/sites/default/files/styles/thumbnail/public/multiple_images/image01_1.jpg?itok=pZU83izg",
        "link" : "<a href=\"/accommodations/fairmont-chateau-lake-louise\">More Detail &raquo;</a>",
        "path" : "/accommodations/fairmont-chateau-lake-louise",
        "type" : "accommodation",
        "latitude" : "51.416787000000",
        "longitude" : "-116.212386400000",
        "location" : "111 Lake Louise Drive Lake Louise AB T0L 1E0 CA",
        "category" : "Hotels and Motels",
        "tid" : "4",
        "marker" : "marker_4"
      }
    }
  ]
}